pnia/__init__.py
pnia-0.0.1a1.dist-info/METADATA
pnia-0.0.1a1.dist-info/WHEEL
pnia-0.0.1a1.dist-info/RECORD
