Metadata-Version: 2.4
Name: pnia
Version: 0.0.1a1
Summary: This project is coming soon.
Author-email: Agents Ready <yizhang.dev+agents-ready@gmail.com>
